nonebot_plugin_dg_lab_play/__init__.py
nonebot_plugin_dg_lab_play/client_manager.py
nonebot_plugin_dg_lab_play/commands/__init__.py
nonebot_plugin_dg_lab_play/commands/players.py
nonebot_plugin_dg_lab_play/commands/pulse_control.py
nonebot_plugin_dg_lab_play/commands/query_status.py
nonebot_plugin_dg_lab_play/commands/show_pulses.py
nonebot_plugin_dg_lab_play/commands/strength_control.py
nonebot_plugin_dg_lab_play/commands/usage.py
nonebot_plugin_dg_lab_play/config.py
nonebot_plugin_dg_lab_play/model.py
nonebot_plugin_dg_lab_play/utils.py
nonebot_plugin_dg_lab_play-1.0.0.dist-info/LICENSE
nonebot_plugin_dg_lab_play-1.0.0.dist-info/METADATA
nonebot_plugin_dg_lab_play-1.0.0.dist-info/WHEEL
nonebot_plugin_dg_lab_play-1.0.0.dist-info/RECORD
