Metadata-Version: 2.1
Name: nonebot-plugin-dg-lab-play
Version: 1.0.0
Summary: nonebot2 机器人插件 - 在群里和大家一起玩郊狼吧！
Home-page: https://dg-lab-play.readthedocs.io
Keywords: nonebot,nonebot2,dg-lab,dg-lab-v3,chatbot,dodo,feishu,kaiheila,onebot,onebot11,onebot12,red,telegram
Author: Ljzd-PRO
Author-email: ljzd@office.ljzd-pro.asia
Requires-Python: >=3.9,<4.0
Classifier: Development Status :: 5 - Production/Stable
Classifier: License :: OSI Approved :: BSD License
Classifier: Operating System :: OS Independent
Classifier: Programming Language :: Python :: 3
Classifier: Programming Language :: Python :: 3.9
Classifier: Programming Language :: Python :: 3.10
Classifier: Programming Language :: Python :: 3.11
Classifier: Programming Language :: Python :: 3.12
Classifier: Topic :: Software Development :: Libraries :: Python Modules
Requires-Dist: nonebot-plugin-alconna (>=0.45.4,<0.46.0)
Requires-Dist: nonebot-plugin-send-anything-anywhere (>=0.6.1,<0.7.0)
Requires-Dist: nonebot2 (>=2.2.0)
Requires-Dist: pydglab-ws (>=1.1.0,<2.0.0)
Requires-Dist: qrcode[pil] (>=7.4.2,<8.0.0)
Project-URL: Documentation, https://dg-lab-play.readthedocs.io
Project-URL: Repository, https://github.com/Ljzd-PRO/nonebot-plugin-dg-lab-play
